xaynet_sdk_python-0.1.0.dist-info/METADATA
xaynet_sdk_python-0.1.0.dist-info/WHEEL
xaynet_sdk/__init__.py
xaynet_sdk/participant.py
xaynet_sdk/async_participant.py
xaynet_sdk/xaynet_sdk.abi3.so
xaynet_sdk_python-0.1.0.dist-info/RECORD
