Metadata-Version: 2.1
Name: xaynet-sdk-python
Version: 0.1.0
Classifier: Development Status :: 3 - Alpha
Classifier: Intended Audience :: Developers
Classifier: Intended Audience :: Information Technology
Classifier: Intended Audience :: Science/Research
Classifier: Topic :: Scientific/Engineering
Classifier: Topic :: Scientific/Engineering :: Artificial Intelligence
Classifier: Topic :: Software Development
Classifier: Topic :: Software Development :: Libraries
Classifier: Topic :: Software Development :: Libraries :: Application Frameworks
Classifier: Topic :: Software Development :: Libraries :: Python Modules
Classifier: License :: OSI Approved :: Apache Software License
Classifier: Programming Language :: Python :: 3 :: Only
Classifier: Programming Language :: Python :: 3.6
Classifier: Programming Language :: Python :: 3.7
Classifier: Programming Language :: Python :: 3.8
Classifier: Programming Language :: Python :: 3.9
Classifier: Operating System :: MacOS :: MacOS X
Classifier: Operating System :: POSIX :: Linux
Requires-Dist: justbackoff (==0.6.0)
Summary: The Xayn Network project is building a privacy layer for machine learning so that AI projects can meet compliance such as GDPR and CCPA. The approach relies on Federated Learning as enabling technology that allows production AI applications to be fully privacy compliant.
Keywords: federated-learning fl ai machine-learning
Home-Page: https://xaynet.dev/
Author: Xayn Engineering <engineering@xaynet.dev>
Author-Email: Xayn Engineering <engineering@xaynet.dev>
License: Apache-2.0
Requires-Python: >=3.6
